odoo/addons/sale_coupon_domain_product_discount/README.rst
odoo/addons/sale_coupon_domain_product_discount/__init__.py
odoo/addons/sale_coupon_domain_product_discount/__manifest__.py
odoo/addons/sale_coupon_domain_product_discount/i18n/sale_coupon_domain_product_discount.pot
odoo/addons/sale_coupon_domain_product_discount/models/__init__.py
odoo/addons/sale_coupon_domain_product_discount/models/coupon_program.py
odoo/addons/sale_coupon_domain_product_discount/models/coupon_reward.py
odoo/addons/sale_coupon_domain_product_discount/models/coupon_rule.py
odoo/addons/sale_coupon_domain_product_discount/models/sale_order.py
odoo/addons/sale_coupon_domain_product_discount/readme/CONTRIBUTORS.rst
odoo/addons/sale_coupon_domain_product_discount/readme/DESCRIPTION.rst
odoo/addons/sale_coupon_domain_product_discount/readme/USAGE.rst
odoo/addons/sale_coupon_domain_product_discount/report/sale_coupon_report_template.xml
odoo/addons/sale_coupon_domain_product_discount/static/description/icon.png
odoo/addons/sale_coupon_domain_product_discount/static/description/index.html
odoo/addons/sale_coupon_domain_product_discount/tests/__init__.py
odoo/addons/sale_coupon_domain_product_discount/tests/test_domain_product_discount.py
odoo/addons/sale_coupon_domain_product_discount/views/coupon_program_views.xml
odoo13_addon_sale_coupon_domain_product_discount-13.0.1.1.0.dist-info/METADATA
odoo13_addon_sale_coupon_domain_product_discount-13.0.1.1.0.dist-info/WHEEL
odoo13_addon_sale_coupon_domain_product_discount-13.0.1.1.0.dist-info/top_level.txt
odoo13_addon_sale_coupon_domain_product_discount-13.0.1.1.0.dist-info/RECORD
